configurable_http_proxy/__init__.py
configurable_http_proxy/cli.py
configurable_http_proxy/configproxy.py
configurable_http_proxy/dbstore.py
configurable_http_proxy/handlers.py
configurable_http_proxy/store.py
configurable_http_proxy/trie.py
configurable_http_proxy/templates/404.html
configurable_http_proxy/templates/500.html
configurable_http_proxy-0.4.0.dist-info/licenses/LICENSE
configurable_http_proxy-0.4.0.dist-info/METADATA
configurable_http_proxy-0.4.0.dist-info/WHEEL
configurable_http_proxy-0.4.0.dist-info/entry_points.txt
configurable_http_proxy-0.4.0.dist-info/top_level.txt
configurable_http_proxy-0.4.0.dist-info/RECORD
