Metadata-Version: 2.4
Name: configurable-http-proxy
Version: 0.4.0
Summary: A python implementation of configurable-http-proxy
Author-email: Corridor Platforms <postmaster@corridorplatforms.com>
License-Expression: Apache-2.0
Project-URL: Homepage, https://github.com/corridor/configurable-http-proxy
Project-URL: Repository, https://github.com/corridor/configurable-http-proxy
Classifier: Intended Audience :: Developers
Classifier: Topic :: Internet :: Proxy Servers
Classifier: Programming Language :: Python :: 3
Classifier: Programming Language :: Python :: 3 :: Only
Classifier: Operating System :: OS Independent
Requires-Python: >=3.8
License-File: LICENSE
Requires-Dist: tornado
Requires-Dist: click
Requires-Dist: python-dateutil
Provides-Extra: sql
Requires-Dist: dataset; extra == "sql"
Dynamic: license-file
